[
  {
    "id": 1,
    "title": "పోగు",
    "icon": "cake",
    "content": [
      "పోగేస్తావా పోగులు పెడతావా",
      "ఇరవై అంగుళాలు గా పుట్టావు",
      "ఆరు అడుగులు పోగేసావు",
      "రెండు సేర్లుగా వచ్చావు",
      "నూరు సేర్లు పోగేసావు",
      "పోగేస్తున్నది ఎవరు పోగు ఎవరు",
      "పోగును పోగులు పెట్టు",
      "పోగేస్తున్నదెవరో కనిపెట్టు",
      "పూర్వ కర్మను తాడుగా చుట్టి",
      "బొంగరంలా వచ్చావు",
      "చుట్ట విడగొడతావా",
      "మరో తాడుకు చుట్టుకుంటావా",
      "పోగేస్తావా పోగుకు పోగులు పెట్టి",
      "పోగేసేవాడికే మూలంలొ ఉన్న  శైవంలొ  ఇక్యమౌతావా"
    ]
  },
  {
    "id": 2,
    "title": "ఆకారం",
    "icon": "format_shapes",
    "content": [
      "అలంకారమొదిలేసిన వానికి పూలదండాలంకరణం",
      "భుజించాల్సిన అవసరం లేని వానికి కొబ్బరి సమర్పణం",
      "ఫలానా రూపమంటూ లేని వానికి లింగ రూపం తత్ చిత్రం",
      "మనిషి ఆకారం నుండి నిర్వికారానికి వెళ్ళడానికి సేతు బంధనం"
    ]
  },
  {
    "id": 3,
    "title": "లక్ష్యం",
    "icon": "navigation",
    "content": [
      "బోర్లా పడితే బొబ్బట్లు ",
      "పాకితే పాయసాలు ",
      "గడప దాటితే గారెలు",
      "అడుగులకు అరిసెలు ",
      "...",
      "సిసువు నుండి బాల్యం ",
      "పండగే మరి ఎదగడం",
      "ఎదిగాక ఎమిటి లక్ష్యం",
      "ఎందుకు ఏదో చేసేయాలన్న జ్వరం   ",
      "...",
      "పరుగులు సరిపోవనా వాహనాలు ",
      "దేనికోసం కింకరులుగా యంత్రాలు",
      "అద్భుతం కోసమా యంత్ర సమూహాలు ",
      "కొత్త అనుభూతి కోసమా తహతహలు",
      "...",
      "కొత్త అనుభూతి క్షణ కాలం",
      "ఎల్లలని తెంచే వాంఛ అంతరంగం",
      "ఒక్కొక్కటిగా వ్యవహరిస్తే అంతులేని కధనం",
      "ఎల్లలే లేని అనుభవం శాశ్వతం"
    ]
  },
  {
    "id": 4,
    "title": "అసలు విషయం",
    "icon": "style",
    "content": [
      "ప్రాణంబులు ఠావులు తప్పాల",
      "మూర్ఛావస్థ రావాల ",
      "నేను అన్నది కరిగి పోవాల",
      "గుండె లోతులోంచి ఆర్తనాదం రావాల ",
      "...",
      "హర హర మహదేవ శంభో శంకర కాని",
      "స్వామియే శరణమయ్యప్పా కాని",
      "అప్పుడు గాని అసలు విషయం కనిపించదని",
      "అంత వరకు చూసేది మాయేనని"
    ]
  },
  {
    "id": 5,
    "title": "దీపావలి",
    "icon": "wb_sunny",
    "content": [
      "పృథ్వి ఉత్తర భాగం సూర్యునకి పెడమొహం పెట్టింది",
      "ఈ భాగంలో జీవరాసులకు మందకోడితనం పట్టింది",
      "ఆకాశ దీపాలు వెలిగించండి ",
      "లెక్కలేనన్ని జ్యోతులు ప్రజ్వలించండి",
      "...",
      "దీపావలి శుభాకాంక్షలు"
    ]
  },
  {
    "id": 6,
    "title": "పంచేంద్రియాలు",
    "icon": "compass_calibration",
    "content": [
      "కంటికి కనిపించింది నిజం కాదు ",
      "చెవికి వినిపించింది అసలు కాదు ",
      "జిహ్వకు తెలిసిన రుచి మొత్తం కాదు ",
      "ముక్కుకి తెలిసిన వాసన సమస్తం కాదు ",
      "స్పర్శ స్పందన అంతా కాదు ",
      "...",
      "పంచేంద్రియాలు పంచ ప్రాణాలు నిలపడానికే ",
      "పంచ భూతాల తత్వం తెలవడానికి పని చెయ్యవే ",
      "మేధస్సు ఉనికిని నిలపడానికే ",
      "ఉనికిని నిలిపేవానిని గ్రహింప పని చెయ్యదే ",
      "ఉపాయం శివైక్య సాధనకి వీటిని సాధనాలుగా  మార్చడమే"
    ]
  },
  {
    "id": 7,
    "title": "జయం, విజయం",
    "icon": "star",
    "content": [
      "సురులెవ్వరు శూరులెవ్వరు",
      "అసురులకు సురకులిచ్చేవారెవ్వరు",
      "చిచ్చు పెట్టేదెవ్వరు ఆపన్నరక్షకులెవ్వరు ",
      "...",
      "ఆట ఎవ్వరిది నియమ నిర్ణేతలెవ్వరు",
      "బరిలొని వారెవ్వరు బయట ప్రేక్షకులెవ్వరు ",
      "జయులెవ్వరు  అపజయులెవ్వరు ",
      "...",
      "ఇద్దరు తల్లుల్లున్నారా ",
      "ఒకే తల్లికి రెండు వర్గాల పిల్లల్లున్నారా ",
      "ప్రీతిపాత్రులే జయం పొందుతున్నారా ",
      "...",
      "పులి జింకను చేజిక్కించుకుంటే జయమా ",
      "జింక తప్పించుకోలెకపోతే అపజయమా ",
      "గొంగూర ఒండుకు తింటే సంబరమా ",
      "...",
      "పోలికలో రెండాకులెక్కువైతె జయం  ",
      "అసలు పోలికే లేక పోతె విజయం   ",
      "యద సడి సృష్టి సడితొ ఏకమైతే సంబరం"
    ]
  },
  {
    "id": 8,
    "title": "అగ్ని",
    "icon": "fireplace",
    "content": [
      "అగ్గి కడుపులో ఉంటే జీర్నం ",
      "అగ్గి తలలో ఉంటే పఠనం",
      "ఎక్కడ అగ్ని రగిలితే మోక్షం ?"
    ]
  },
  {
    "id": 9,
    "title": "రహస్య౦",
    "icon": "device_unknown",
    "content": [
      "సోది చెబుతానమ్మ సోది చెబుతాను",
"ఉన్నది ఉన్నట్టు లేనిది లేనట్టు చెబుతాను ",
"కవి కోకిల రామాయణం చెబుతాను  ",
"అష్టాదశ పురాణాలు చెబుతాను ",
"...",
"భాగవతం చదువుతాను ",
"భగవద్గీత శ్లోకాలు చెబుతాను   ",
"అరుదైన మంత్రాలు ఉచ్ఛరిస్తాను  ",
"వాటి భాష్యం తెలుసుకుంటాను  ",
"...",
"అర్థాలు చదువుతూ  చెబుతాను  ",
"ప్రవచనాలు వింటాను ఆహా అంటాను ",
"గుడి గొపురంపై శిఖరాన్ని చూస్తాను ",
"కొలువున్న దేవత వైశిష్ట్యం కనుగొంటాను",
"...",
"ఇన్ని చేసినా అనుభవం మారలేదు  ",
"ఒడుదుడుకులకు నలిగిపోవడమాగలేదు  ",
"పైన సమాధానాలకు సమాధాన పడలేక  ",
"ఏం చెయ్యాలొ తెలియక ఎలా చెయ్యాలో తోచక ",
"...",
"సతమతమయ్యాను అయ్యా అని అర్ధించాను  ",
"కిటుకు జవాబులో లేదని ",
"పదునైన ప్రశ్నలొ ఉందని ",
"తెలుసుకోలేక  తికమక పడ్డాను ",
"...",
"బ్రహ్మాండంలో ఎన్నో రహస్య గదులు ",
"తలుపులకన్నీ రక రకాల తాళాలు    ",
"గదిలొ ఏముందో చదివితే సమాచారం ",
"ప్రశ్న అనే చెవ్వితో తెరిస్తే అనుభవం   ",
"...",
"ఒక్కో తాళానికి ఒక్కో చెవ్వి ",
"ఎంతో నేర్పుతో చెక్కాలి  ",
"జాగర్తగా అరగ దీయ్యాలి  ",
"పలు మార్లు ప్రయత్నించాలి"
    ]
  },
  {
    "id": 10,
    "title": "అలవాటులొ పొరపాటుగా",
    "icon": "repeat",
    "content": [
      "అలవాటులొ పొరపాటుగా",
"పొరపాటే అలవాటుగా",
"బ్రతుకే అలవాటుగా ",
"...",
"కష్టం లెకుండా సాగనిచ్చేట్టుగా",
"చేసిందే చేసేస్తే చాలుగా",
"అనుకుంటే సరిపోదుగా ",
"...",
"కడుపు నిండేదాకా",
"అంగలుపొంగలుగా ",
"ఆ తరవాత ఒక్క సారిగా   ",
"...",
"ఉన్నంత సరిపొదనిపించదా   ",
" ఇంతకింతవ్వాలనిపించదా  ",
"పూర్ణత్వం ఎలా వచ్చేననిపించదా   ",
"...",
"ఇది ఉంటే అది లేదు ",
"అది ఉంటే ఇది లేదు ",
"రెండూ వస్తే మూడోది లేదు ",
"...",
"ఈ దాహం తీరేదెలాచెప్మా ",
"ఈ వెల్తి సృష్టి నియమమా ",
"లేక మానవ అయోమయమా ",
"...",
"సమస్తం స్వాధీనం ",
"ఐతేనే  శమియించడం  ",
"అది ఎలా సాధ్యం ",
"...",
"సృష్టి సముద్రం ",
"మనిషి బొట్టు మాత్రం ",
"ఏమిటి మార్గం ",
"...",
"బొట్టులో సముద్రమా ",
"సముద్రంలో బొట్టా ",
"ఐక్యమయ్యకా తేడా తెలిసేనా ",
"...",
"బొట్టు బొట్టుగా ఉండాలంటే ",
"దాహం తీరదంతే ",
"ఉనికిని ఒదులుకుంటే సంపూర్ణమే     ",
"...",
"ఆహా ఏమి అద్భుతం ",
"మానవ జీవితం",
"మహత్తర అవకాశం ",
"...",
"బొట్టుని బొట్టులా ఉంచుతూ ",
"సంద్రాన్ని అనుభవిస్తూ ",
"కూర్మంలా నేలా నీట సంచరిస్తూ ",
"...",
"ఇటు సృష్టిలో భాగంగా ",
"అటు సృష్తికర్తగా  ",
"రెండిటిగా రెండు ఒక్కటిగా  ",
"...",
"ఉనికి శివాంశగా ",
"అంత్యమున ఐక్యమవ్వంగా ",
"శివోహంగా ముక్తిని పొందగా"
    ]
  },
  {
    "id": 11,
    "title": "అమరిక",
    "icon": "view_module",
    "content": [
      "ముందు తీపి  చివర  కారం ",
      "వెనకది ముందు ముందుది వెనక  ",
      "ఇలా ఐతేనే అలా ఐతేనే ఎలా ఐతేనే    ",
      "అమరికలో ఏముందా లేక అంతా ఉందా  ",
      "...",
      "పెద్ద తేడా ఏముండదా  ",
      "కొంచుమటూ ఇటూ నడిచి పోతుందా    ",
      "కిందది పైనా పైనది కింద అయ్యిందా        ",
      "అమరికలో ఏముందా లేక అంతా ఉందా  ",
      "...",
      "అమరికలోనే శృష్టి రహస్యం దాగుంది  ",
      "సౌర కుటుంబం కాని బ్రహ్మాండం కాని  ",
      "కన్నుల విందవ్వనీ వీనుల విందవ్వనీ  ",
      "మాధుర్యమంతా అమరిక లోనె ఉన్నది   ",
      "...",
      "అమావాస్య పౌర్నమి  వెలుగు నీడా  ",
      "తాళము చెవ్వి పదము పద్యము  ",
      "మనిషి ఉనికి  సమస్థ జీవరాసులు స్థిథీ  ",
      "శృష్టి రూపమంతా ఆ అమరికలోనే ఉన్నది   ",
      "...",
      "కురుక్షేత్రములో చక్రవ్యూహము  ",
      "అభిమన్యుని చేతిలొ బండి చక్రము  ",
      "శంఖం సుదర్శనం శివుని చేతిలొ త్రిశూలం    ",
      "వైషిష్ట్యమంతా అమరికలొనే ఉన్నది   ",
      "...",
      "వినా దైన్యేన జీవనం సునాయాసేన మరణం   ",
      "అనుదినం చేశే పని కష్టమా సుఖమా  ",
      "చీమ కాళ్ళు సీతా కోక చిలుక రెక్కలు  ",
      "మర్మమంతా అమరిక లొనే ఉన్నది   ",
      "...",
      "మానవుని వివేకము మౌడ్యము    ",
      "రసం భావం అతని అనుభవం ",
      "పశువౌతాడా పశుపతౌతాడా  ",
      "ఎంచుకున్న అమరిక తేలుస్తుంది   ",
      "...",
      "రాగం శృష్టి నిర్ణయం భావం అనుభవం   ",
      "సరైన తాళం పట్టుకుంటే  యొగం   ",
      "భావ రాగ తాల సమ్మేలణం   ",
      "భారతం జీవన సంవిధానం  "
    ]
  },
  {
    "id": 12,
    "title": "నారసింహా",
    "icon": "send",
    "content": [
      "ప్రహ్లాదుడు అంతటా శ్రిమహావిష్ణువే అంటే ",
      "ఎక్కడాలేడని హిరణ్య కశ్యపుడు బెదిరించే",
      "ఆవిర్భావ సమయం ఆసన్నమాయనని శ్రీహరి గ్రహించే ",
      "సృష్టి గర్భమంతటా నిండి నిబిడీకృతమై ఆక్రమించే  ",
      "...",
      "ఎచ్చోట  దానవుడు చూప మన్న ",
      "అచ్చోటనే ప్రత్యక్షమౌ విధమున ",
      "అడిగిన వెంటనే వచ్చు రీతిన ",
      "వెలువడేందుకు ఉత్తర క్షణాన్న     ",
      "...",
      "ఆహా ఏమి ఆ ఉత్తమోత్తమ క్షణం  ",
      "ఊహకందనిదీ  వర్ణనాతీతం ",
      "సమస్త జగత్తు దేవాలయం గా మారడం   ",
      "కూర్చున్న చోటే గర్భ గృహం"
    ]
  }
]
